cccalendar.py
colourutils.py
datautils.py
dateutils.py
run.py
categorical_colour_calendar-0.1.0.dist-info/LICENSE
categorical_colour_calendar-0.1.0.dist-info/METADATA
categorical_colour_calendar-0.1.0.dist-info/WHEEL
categorical_colour_calendar-0.1.0.dist-info/top_level.txt
categorical_colour_calendar-0.1.0.dist-info/RECORD
