Metadata-Version: 2.1
Name: categorical-colour-calendar
Version: 0.1.0
Summary: Library for drawing monthly calendars and highlighting dates from categorical data
Home-page: https://github.com/erichards97/categorical-colour-calendar
Author: Edward Richards
Author-email: 
License: UNKNOWN
Platform: UNKNOWN
Classifier: Programming Language :: Python :: 3
Classifier: Programming Language :: Python :: 3.7
Classifier: Programming Language :: Python :: 3.8
Classifier: Programming Language :: Python :: 3.9
Classifier: Development Status :: 3 - Alpha
Classifier: License :: OSI Approved :: MIT License
Classifier: Operating System :: OS Independent
Requires-Dist: pandas (>=1.2.1)
Requires-Dist: matplotlib (>=3.3.4)
Provides-Extra: dev
Requires-Dist: check-manifest (>=0.46) ; extra == 'dev'
Requires-Dist: twine (>=3.3.0) ; extra == 'dev'
Requires-Dist: wheel (>=0.36.2) ; extra == 'dev'
Requires-Dist: pytest (>=6.2.2) ; extra == 'dev'
Requires-Dist: tox (>=3.23.0) ; extra == 'dev'
Provides-Extra: docs
Requires-Dist: sphinx (==3.4.3) ; extra == 'docs'
Provides-Extra: tests
Requires-Dist: pytest (>=6.2.2) ; extra == 'tests'
